odoo/addons/ssi_project_custom_information/README.rst
odoo/addons/ssi_project_custom_information/__init__.py
odoo/addons/ssi_project_custom_information/__manifest__.py
odoo/addons/ssi_project_custom_information/models/__init__.py
odoo/addons/ssi_project_custom_information/models/project_project.py
odoo/addons/ssi_project_custom_information/models/project_task.py
odoo/addons/ssi_project_custom_information/static/description/icon.png
odoo14_addon_ssi_project_custom_information-14.0.1.1.1.dist-info/METADATA
odoo14_addon_ssi_project_custom_information-14.0.1.1.1.dist-info/WHEEL
odoo14_addon_ssi_project_custom_information-14.0.1.1.1.dist-info/top_level.txt
odoo14_addon_ssi_project_custom_information-14.0.1.1.1.dist-info/RECORD
